{
    "title": "Anith's blog",
    "url": "https://localhost:8080/",
    "language": "en",
    "description": "Anith writes about feels, heals, design, and creativity.",
    "feed": {
        "subtitle": "",
        "filename": "feed.xml",
        "path": "/feed/feed.xml",
        "id": "https://localhost:8080/"
    },
    "jsonfeed": {
        "path": "/feed/feed.json",
        "url": "https://localhost:8080/feed/feed.json"
    },
    "author": {
        "name": "Anith Vishwanath",
        "email": "anithvis@gmail.com"
    }
}